[
    {
      "id": 1,
      "name": "Red",
      "image": "https://tse2.mm.bing.net/th?id=OIP.I8iT2m-wqSJ5SgdEiYUp5QHaDt&pid=Api&P=0&w=342&h=172"
    },
    {
      "id": 2,
      "name": "Blue",
      "image": "https://tse1.mm.bing.net/th?id=OIP.iQ9_koubO2DXnpD7UIXOowHaHa&pid=Api&P=0&w=300&h=300"
    },
    {
      "id": 3,
      "name": "Green",
      "image": "https://tse3.mm.bing.net/th?id=OIP.PShIU8_3Q7bIq87HgRvHsQHaEo&pid=Api&P=0&w=254&h=160"
    },
    {
      "id": 4,
      "name": "Yellow",
      "image": "https://tse2.mm.bing.net/th?id=OIP.EiUYkcp9f3Vt1aEwhM8ZGAHaHa&pid=Api&P=0&w=300&h=300"
    },
    {
      "id": 5,
      "name": "Brown",
      "image": "http://moziru.com/images/square-clipart-brown-3.png"
    },
    {
      "id": 6,
      "name": "Purple",
      "image": "http://www.candlechem.com/images/D155violet.gif"
    },
    {
      "id": 7,
      "name": "Orange",
      "image": "https://tse1.mm.bing.net/th?id=OIP.AfeemgVOkWW4xk4enBTB9gHaFj&pid=Api&P=0&w=236&h=178"
    },
    {
      "id": 8,
      "name": "Pink",
      "image": "http://www.candlesandsupplies.net/Pink-Color-Block-image.gif"
    },
    {
      "id": 9,
      "name": "Black",
      "image": "http://2.bp.blogspot.com/-2c_KyF-gqqA/T31eu9z_7iI/AAAAAAAAAVQ/znSbt2c3Qpo/s1600/black%2B4.gif"
    }
  ]
  